<?xml version="1.0" encoding="utf-8"?>
<!DOCTYPE hibernate-mapping PUBLIC "-//Hibernate/Hibernate Mapping DTD 3.0//EN"
"http://hibernate.sourceforge.net/hibernate-mapping-3.0.dtd">
<!-- 
    Mapping file autogenerated by MyEclipse Persistence Tools
-->
<hibernate-mapping>
    <class name="com.sys.exam.database.bean.User" table="user" catalog="exambase">
        <id name="userId" type="long">
            <column name="userId" />
            <generator class="native" />
        </id>
        <property name="userName" type="string">
            <column name="userName" length="50" not-null="true" />
        </property>
        <property name="userAccount" type="string">
            <column name="userAccount" length="50" not-null="true" />
        </property>
        <property name="userPassword" type="string">
            <column name="userPassword" length="50" not-null="true" />
        </property>
        <property name="userRole" type="integer">
            <column name="userRole" not-null="true" />
        </property>
        <property name="usermail" type="string">
            <column name="usermail" length="100" />
        </property>
        <set name="userExams" inverse="true">
            <key>
                <column name="ue_userId" not-null="true" />
            </key>
            <one-to-many class="com.sys.exam.database.bean.UserExam" />
        </set>
        <set name="userGroupRels" inverse="true">
            <key>
                <column name="ugr_userId" not-null="true" />
            </key>
            <one-to-many class="com.sys.exam.database.bean.UserGroupRel" />
        </set>
    </class>
</hibernate-mapping>
